roadrunnerloopdetect/__init__.py
roadrunnerloopdetect/roadrunnerloopdetect.py
roadrunnerloopdetect-0.0.2.dist-info/LICENSE
roadrunnerloopdetect-0.0.2.dist-info/METADATA
roadrunnerloopdetect-0.0.2.dist-info/WHEEL
roadrunnerloopdetect-0.0.2.dist-info/top_level.txt
roadrunnerloopdetect-0.0.2.dist-info/RECORD
